datasus_db/__init__.py
datasus_db/cnv.py
datasus_db/datasources/__init__.py
datasus_db/datasources/auxiliar.py
datasus_db/datasources/ibge_pop.py
datasus_db/datasources/ibge_pop_tcu.py
datasus_db/datasources/po.py
datasus_db/datasources/sia_pa.py
datasus_db/datasources/sih_rd.py
datasus_db/datasources/sih_sp.py
datasus_db/datasources/sim_do.py
datasus_db/datasus.py
datasus_db/db.py
datasus_db/dbf.py
datasus_db/ftp.py
datasus_db/pl_utils.py
datasus_db/utils.py
datasus_db/views/__init__.py
datasus_db/views/ibge_piramide_etaria.py
datasus_db-0.1.3.dist-info/LICENSE
datasus_db-0.1.3.dist-info/METADATA
datasus_db-0.1.3.dist-info/WHEEL
datasus_db-0.1.3.dist-info/RECORD
