Metadata-Version: 2.1
Name: datasus-db
Version: 0.1.3
Summary: Download and import DATASUS's public data to a DuckDB database
Home-page: https://github.com/mymatsubara/datasus-db
License: MIT
Keywords: datasus,duckdb,data science,database
Author: Murilo Matsubara
Author-email: murilo.matsubara@gmail.com
Requires-Python: >=3.11,<4.0
Classifier: License :: OSI Approved :: MIT License
Classifier: Operating System :: OS Independent
Classifier: Programming Language :: Python :: 3
Classifier: Programming Language :: Python :: 3.11
Classifier: Programming Language :: Python :: 3.12
Requires-Dist: datasus-dbc (>=0.1.1,<0.2.0)
Requires-Dist: dbfread (>=2.0.7,<3.0.0)
Requires-Dist: duckdb (>=0.9.2,<0.10.0)
Requires-Dist: polars (>=0.19.19,<0.20.0)
Requires-Dist: pyarrow (>=14.0.1,<15.0.0)
Project-URL: Documentation, https://mymatsubara.github.io/datasus-db/datasus_db.html
Project-URL: Repository, https://github.com/mymatsubara/datasus-db
